MANIFEST.in
README.md
pyproject.toml
setup.py
amuse_fi.egg-info/PKG-INFO
amuse_fi.egg-info/SOURCES.txt
amuse_fi.egg-info/dependency_links.txt
amuse_fi.egg-info/requires.txt
amuse_fi.egg-info/top_level.txt
src/amuse/community/fi/Makefile
src/amuse/community/fi/README
src/amuse/community/fi/__init__.py
src/amuse/community/fi/_version.py
src/amuse/community/fi/interface.f90
src/amuse/community/fi/interface.py
src/amuse/community/fi/map_interface.f90
src/amuse/community/fi/patch_globals_dot_h.py
src/amuse/community/fi/data/README.txt
src/amuse/community/fi/data/input/C.Hcool
src/amuse/community/fi/data/input/C.cool
src/amuse/community/fi/data/input/Fe.Hcool
src/amuse/community/fi/data/input/Fe.cool
src/amuse/community/fi/data/input/H.Hcool
src/amuse/community/fi/data/input/H.cool
src/amuse/community/fi/data/input/H2.H2cool
src/amuse/community/fi/data/input/H2.HH2cool
src/amuse/community/fi/data/input/H2.Hcool
src/amuse/community/fi/data/input/He.Hcool
src/amuse/community/fi/data/input/He.cool
src/amuse/community/fi/data/input/N.Hcool
src/amuse/community/fi/data/input/N.cool
src/amuse/community/fi/data/input/Ne.Hcool
src/amuse/community/fi/data/input/Ne.cool
src/amuse/community/fi/data/input/O.Hcool
src/amuse/community/fi/data/input/O.cool
src/amuse/community/fi/data/input/Si.Hcool
src/amuse/community/fi/data/input/Si.cool
src/amuse/community/fi/data/input/bct_02_10.halo
src/amuse/community/fi/data/input/bct_12_10_023.halo
src/amuse/community/fi/data/input/bct_18_06_10.halo
src/amuse/community/fi/data/input/bct_2_10_0045.halo
src/amuse/community/fi/data/input/burk_1.25.halo
src/amuse/community/fi/data/input/burk_1.8.halo
src/amuse/community/fi/data/input/burk_2.2.halo
src/amuse/community/fi/data/input/burkct_4_20_02.halo
src/amuse/community/fi/data/input/burkct_4_20_04.halo
src/amuse/community/fi/data/input/extinctionlaw
src/amuse/community/fi/data/input/hk_102_2.halo
src/amuse/community/fi/data/input/hk_124_12.halo
src/amuse/community/fi/data/input/hk_144_12.halo
src/amuse/community/fi/data/input/hk_181_2.halo
src/amuse/community/fi/data/input/hk_195_2.halo
src/amuse/community/fi/data/input/hk_50_2.halo
